rf_perm_feat_import/RFFeatureImportance.py
rf_perm_feat_import/__init__.py
rf_perm_feat_import-0.1.dist-info/DESCRIPTION.rst
rf_perm_feat_import-0.1.dist-info/METADATA
rf_perm_feat_import-0.1.dist-info/RECORD
rf_perm_feat_import-0.1.dist-info/WHEEL
rf_perm_feat_import-0.1.dist-info/metadata.json
rf_perm_feat_import-0.1.dist-info/top_level.txt
