Metadata-Version: 2.0
Name: rf-perm-feat-import
Version: 0.1
Summary: Random Forest Permutate Feature Importance
Home-page: https://github.com/pjh2011/sklearn_perm_feat_import
Author: Peter Hughes
Author-email: pethug210@gmail.com
License: MIT
Platform: UNKNOWN
Requires-Dist: numpy
Requires-Dist: sklearn
